xiaoapi_sqlalchemy/__init__.py
xiaoapi_sqlalchemy/commands.py
xiaoapi_sqlalchemy/crud.py
xiaoapi_sqlalchemy/database.py
xiaoapi_sqlalchemy/dependencies.py
xiaoapi_sqlalchemy/migrate.py
xiaoapi_sqlalchemy/model_base.py
xiaoapi_sqlalchemy-0.0.5.dist-info/LICENSE
xiaoapi_sqlalchemy-0.0.5.dist-info/METADATA
xiaoapi_sqlalchemy-0.0.5.dist-info/WHEEL
xiaoapi_sqlalchemy-0.0.5.dist-info/top_level.txt
xiaoapi_sqlalchemy-0.0.5.dist-info/RECORD
